<?xml version="1.0" encoding="utf-8" ?>
<dwsync>
<file name="reset.css" server="kimsuntae.com" local="131074856400000000" remote="131074856400000000" Dst="0" />
<file name="style.css" server="kimsuntae.com" local="131074856400000000" remote="131074856400000000" Dst="0" />
<file name="slider.css" server="kimsuntae.com" local="131074856400000000" remote="131074856400000000" Dst="0" />
<file name="responsive.css" server="kimsuntae.com" local="131075458510387244" remote="131074990200000000" Dst="0" />
<file name="menu.css" server="kimsuntae.com" local="131074856400000000" remote="131074856400000000" Dst="0" />
<file name="SATURDAY.CSS" server="kimsuntae.com" local="131075434811599475" remote="131074856400000000" Dst="0" />
<file name="correction.css" server="kimsuntae.com" local="131075434835450839" remote="131074856400000000" Dst="0" />
<file name="base.css" server="kimsuntae.com" local="131075434837910980" remote="131074856400000000" Dst="0" />
<file name="main.css" server="kimsuntae.com" local="131075435130695137" remote="131074856400000000" Dst="0" />
<file name="normalize.css" server="kimsuntae.com" local="131075435133295141" remote="131074856400000000" Dst="0" />
<file name="photo-viewer.css" server="kimsuntae.com" local="131075435146395159" remote="131074856400000000" Dst="0" />
</dwsync>